afmparser/AFMLexer.py
afmparser/AFMListener.py
afmparser/AFMParser.py
afmparser/__init__.py
afmparser/main.py
afmparser-1.0.1.dist-info/LICENSE
afmparser-1.0.1.dist-info/METADATA
afmparser-1.0.1.dist-info/WHEEL
afmparser-1.0.1.dist-info/top_level.txt
afmparser-1.0.1.dist-info/zip-safe
afmparser-1.0.1.dist-info/RECORD
