Metadata-Version: 2.1
Name: afmparser
Version: 1.0.1
Summary: This module provides a get_tree function to obtain an ANTLR4 parse-tree from a AFM-defined feature model
Home-page: https://github.com/flamapy/afmparser
Author: José A. Galindo
Author-email: jagalindo@us.es
License: GNU General Public License v3 (GPLv3)
Classifier: Programming Language :: Python :: 3
Classifier: License :: OSI Approved :: GNU General Public License v3 (GPLv3)
Classifier: Operating System :: OS Independent
Requires-Python: >=3.0
License-File: LICENSE
Requires-Dist: antlr4-python3-runtime ==4.13.1
